sn_restapi_wrapper/__init__.py
sn_restapi_wrapper/fetch_data.py
sn_restapi_wrapper-1.1.3.dist-info/METADATA
sn_restapi_wrapper-1.1.3.dist-info/WHEEL
sn_restapi_wrapper-1.1.3.dist-info/license.txt
sn_restapi_wrapper-1.1.3.dist-info/top_level.txt
sn_restapi_wrapper-1.1.3.dist-info/RECORD
